<?xml version="1.0" encoding="utf-8" ?>
<dwsync>
<file name="CUN1.jpg" server="ftp.promocoesdepassagemaerea.com.br" local="132749216448516439" remote="132491052000000000" Dst="0" />
<file name="CUN3.jpg" server="ftp.promocoesdepassagemaerea.com.br" local="132749216450488158" remote="132491052000000000" Dst="0" />
<file name="CUN2.jpg" server="ftp.promocoesdepassagemaerea.com.br" local="132749216451090860" remote="132491052000000000" Dst="0" />
<file name="CUN4.jpg" server="ftp.promocoesdepassagemaerea.com.br" local="132749216451434342" remote="132491052000000000" Dst="0" />
<file name="CUN5.jpg" server="ftp.promocoesdepassagemaerea.com.br" local="132749216453953318" remote="132491052000000000" Dst="0" />
<file name="CUN1.jpg" server="ftp.vps-pdpa.provisorio.ws" local="132749216448516439" remote="132749893800000000" Dst="0" />
<file name="CUN3.jpg" server="ftp.vps-pdpa.provisorio.ws" local="132749216450488158" remote="132749893800000000" Dst="0" />
<file name="CUN5.jpg" server="ftp.vps-pdpa.provisorio.ws" local="132749216453953318" remote="132749893800000000" Dst="0" />
<file name="CUN4.jpg" server="ftp.vps-pdpa.provisorio.ws" local="132749216451434342" remote="132749893800000000" Dst="0" />
<file name="CUN2.jpg" server="ftp.vps-pdpa.provisorio.ws" local="132749216451090860" remote="132749893800000000" Dst="0" />
<file name="CUN2.jpg" server="ftp.novopdpa.tecnologia.ws" local="132749216451090860" remote="132754404000000000" Dst="0" />
<file name="CUN3.jpg" server="ftp.novopdpa.tecnologia.ws" local="132749216450488158" remote="132754404000000000" Dst="0" />
<file name="CUN4.jpg" server="ftp.novopdpa.tecnologia.ws" local="132749216451434342" remote="132754404000000000" Dst="0" />
<file name="CUN1.jpg" server="ftp.novopdpa.tecnologia.ws" local="132749216448516439" remote="132754404000000000" Dst="0" />
<file name="CUN5.jpg" server="ftp.novopdpa.tecnologia.ws" local="132749216453953318" remote="132754404000000000" Dst="0" />
</dwsync>