<?xml version="1.0" encoding="utf-8" ?>
<dwsync>
<file name="ZRH1.jpg" server="ftp.promocoesdepassagemaerea.com.br" local="132749218062384944" remote="132491052000000000" Dst="0" />
<file name="ZRH4.jpg" server="ftp.promocoesdepassagemaerea.com.br" local="132749218063203567" remote="132491052000000000" Dst="0" />
<file name="ZRH5.jpg" server="ftp.promocoesdepassagemaerea.com.br" local="132749218066531965" remote="132491052000000000" Dst="0" />
<file name="ZRH6.jpg" server="ftp.promocoesdepassagemaerea.com.br" local="132484648961273144" remote="132484258200000000" Dst="0" />
<file name="ZRH7.jpg" server="ftp.promocoesdepassagemaerea.com.br" local="132749218066617002" remote="132491052000000000" Dst="0" />
<file name="ZRH8.jpg" server="ftp.promocoesdepassagemaerea.com.br" local="132484648962111555" remote="132484258800000000" Dst="0" />
<file name="ZRH9.jpg" server="ftp.promocoesdepassagemaerea.com.br" local="132749218067641758" remote="132491052000000000" Dst="0" />
<file name="ZRH1.jpg" server="ftp.vps-pdpa.provisorio.ws" local="132749218062384944" remote="132749896800000000" Dst="0" />
<file name="ZRH4.jpg" server="ftp.vps-pdpa.provisorio.ws" local="132749218063203567" remote="132749896800000000" Dst="0" />
<file name="ZRH7.jpg" server="ftp.vps-pdpa.provisorio.ws" local="132749218066617002" remote="132749896800000000" Dst="0" />
<file name="ZRH8.jpg" server="ftp.vps-pdpa.provisorio.ws" local="132484648962111555" remote="132749896800000000" Dst="0" />
<file name="ZRH5.jpg" server="ftp.vps-pdpa.provisorio.ws" local="132749218066531965" remote="132749896800000000" Dst="0" />
<file name="ZRH6.jpg" server="ftp.vps-pdpa.provisorio.ws" local="132484648961273144" remote="132749896800000000" Dst="0" />
<file name="ZRH9.jpg" server="ftp.vps-pdpa.provisorio.ws" local="132749218067641758" remote="132749896800000000" Dst="0" />
<file name="ZRH1.jpg" server="ftp.novopdpa.tecnologia.ws" local="132749218062384944" remote="132754407000000000" Dst="0" />
<file name="ZRH4.jpg" server="ftp.novopdpa.tecnologia.ws" local="132749218063203567" remote="132754407000000000" Dst="0" />
<file name="ZRH6.jpg" server="ftp.novopdpa.tecnologia.ws" local="132484648961273144" remote="132754407000000000" Dst="0" />
<file name="ZRH5.jpg" server="ftp.novopdpa.tecnologia.ws" local="132749218066531965" remote="132754407000000000" Dst="0" />
<file name="ZRH7.jpg" server="ftp.novopdpa.tecnologia.ws" local="132749218066617002" remote="132754407000000000" Dst="0" />
<file name="ZRH9.jpg" server="ftp.novopdpa.tecnologia.ws" local="132749218067641758" remote="132754407000000000" Dst="0" />
<file name="ZRH8.jpg" server="ftp.novopdpa.tecnologia.ws" local="132484648962111555" remote="132754407000000000" Dst="0" />
</dwsync>